mastercard_installments_fi-0.0.4.dist-info/DESCRIPTION.rst
mastercard_installments_fi-0.0.4.dist-info/METADATA
mastercard_installments_fi-0.0.4.dist-info/RECORD
mastercard_installments_fi-0.0.4.dist-info/WHEEL
mastercard_installments_fi-0.0.4.dist-info/metadata.json
mastercard_installments_fi-0.0.4.dist-info/top_level.txt
mastercardinstallmentsfi/__init__.py
mastercardinstallmentsfi/backgroundconfiguration.py
mastercardinstallmentsfi/eligibilityandcalculator.py
mastercardinstallmentsfi/eligibilityandinstallmentplan.py
mastercardinstallmentsfi/resourceconfig.py
